MANIFEST.in
README.md
setup.py
src/PyWMOFiles/BUFR.py
src/PyWMOFiles/Error.py
src/PyWMOFiles/__init__.py
src/PyWMOFiles.egg-info/PKG-INFO
src/PyWMOFiles.egg-info/SOURCES.txt
src/PyWMOFiles.egg-info/dependency_links.txt
src/PyWMOFiles.egg-info/top_level.txt
src/PyWMOFiles/tables/BUFR_tblB.json
src/PyWMOFiles/tables/BUFR_tblD.json