Metadata-Version: 1.1
Name: PyWMOFiles
Version: 0.0.1.1
Summary: Files defined by WMO  read module
Home-page: https://github.com/yakawa/PyWMOFiles
Author: KAWASAKI Yasukazu (yakawa)
Author-email: kawasaki@dev.kawa1128.jp
License: MIT
Keywords: BUFR,WMO,Parser
Platform: UNKNOWN
Classifier: Development Status :: 3 - Alpha
Classifier: Intended Audience :: Science/Research
Classifier: License :: OSI Approved :: MIT License
Classifier: Operating System :: OS Independent
Classifier: Programming Language :: Python
Classifier: Programming Language :: Python :: 3
Classifier: Topic :: Software Development :: Libraries :: Python Modules
Classifier: Topic :: Scientific/Engineering :: Atmospheric Science
